{
    "openapi": "3.1.0",
    "info": {
        "title": "Auto-generated OAS of RealWorld using OOPS",
        "version": "1.0.0"
    },
    "paths": {
        "/api/articles": {
            "get": {
                "operationId": "apiArticlesGet",
                "parameters": [
                    {
                        "required": false,
                        "style": "form",
                        "explode": true,
                        "schema": {
                            "$ref": "#/components/schemas/801051deb0ab9f05cdcc2330d9ff7c98"
                        },
                        "name": "tag",
                        "in": "query"
                    },
                    {
                        "required": false,
                        "style": "form",
                        "explode": true,
                        "schema": {
                            "$ref": "#/components/schemas/801051deb0ab9f05cdcc2330d9ff7c98"
                        },
                        "name": "author",
                        "in": "query"
                    },
                    {
                        "required": false,
                        "style": "form",
                        "explode": true,
                        "schema": {
                            "$ref": "#/components/schemas/801051deb0ab9f05cdcc2330d9ff7c98"
                        },
                        "name": "favorited",
                        "in": "query"
                    },
                    {
                        "required": false,
                        "style": "form",
                        "explode": true,
                        "schema": {
                            "$ref": "#/components/schemas/801051deb0ab9f05cdcc2330d9ff7c98"
                        },
                        "name": "limit",
                        "in": "query"
                    },
                    {
                        "required": false,
                        "style": "form",
                        "explode": true,
                        "schema": {
                            "$ref": "#/components/schemas/801051deb0ab9f05cdcc2330d9ff7c98"
                        },
                        "name": "offset",
                        "in": "query"
                    }
                ],
                "responses": {
                    "200": {
                        "description": "OK",
                        "content": {
                            "*/*": {
                                "schema": {
                                    "$ref": "#/components/schemas/332e82c6bdd5ac3bf5ea0510ba61025f"
                                }
                            }
                        }
                    },
                    "404": {
                        "description": "Invalid param",
                        "content": {}
                    }
                }
            },
            "post": {
                "operationId": "apiArticlesPost",
                "parameters": [
                    {
                        "description": "JWT token",
                        "required": true,
                        "style": "simple",
                        "explode": false,
                        "schema": {
                            "$ref": "#/components/schemas/801051deb0ab9f05cdcc2330d9ff7c98"
                        },
                        "name": "Authorization",
                        "in": "header"
                    }
                ],
                "requestBody": {
                    "description": "Article to create",
                    "content": {
                        "*/*": {
                            "schema": {
                                "$ref": "#/components/schemas/4d3603a0b1508e557c000c21e6de2ad5"
                            }
                        }
                    },
                    "required": true
                },
                "responses": {
                    "201": {
                        "description": "Created",
                        "content": {
                            "*/*": {
                                "schema": {
                                    "$ref": "#/components/schemas/06865e445c5dc508f4e842f390217f80"
                                }
                            }
                        }
                    },
                    "422": {
                        "description": "Validation or database error",
                        "content": {
                            "*/*": {
                                "schema": {
                                    "$ref": "#/components/schemas/207b98600ff36022b288945721524c2c"
                                }
                            }
                        }
                    }
                },
                "x-codegen-request-body-name": "body"
            }
        },
        "/articles/{slug}": {
            "put": {
                "operationId": "articlesSlugPut",
                "parameters": [
                    {
                        "required": true,
                        "style": "simple",
                        "explode": false,
                        "schema": {
                            "$ref": "#/components/schemas/801051deb0ab9f05cdcc2330d9ff7c98"
                        },
                        "name": "slug",
                        "in": "path"
                    }
                ],
                "requestBody": {
                    "content": {
                        "*/*": {
                            "schema": {
                                "$ref": "#/components/schemas/f3dbb1c7998397f9739dd8ca035645bc"
                            }
                        }
                    },
                    "required": true
                },
                "responses": {
                    "200": {
                        "description": "OK",
                        "content": {
                            "*/*": {
                                "schema": {
                                    "$ref": "#/components/schemas/b86f86ff4e88d014b319f07dcbcaa18a"
                                }
                            }
                        }
                    },
                    "404": {
                        "description": "Not Found",
                        "content": {
                            "*/*": {
                                "schema": {
                                    "$ref": "#/components/schemas/207b98600ff36022b288945721524c2c"
                                }
                            }
                        }
                    },
                    "422": {
                        "description": "Validation error",
                        "content": {
                            "*/*": {
                                "schema": {
                                    "$ref": "#/components/schemas/207b98600ff36022b288945721524c2c"
                                }
                            }
                        }
                    }
                },
                "x-codegen-request-body-name": "body"
            },
            "delete": {
                "operationId": "articlesSlugDelete",
                "parameters": [
                    {
                        "required": true,
                        "style": "simple",
                        "explode": false,
                        "schema": {
                            "$ref": "#/components/schemas/801051deb0ab9f05cdcc2330d9ff7c98"
                        },
                        "name": "slug",
                        "in": "path"
                    }
                ],
                "responses": {
                    "200": {
                        "description": "OK",
                        "content": {
                            "*/*": {
                                "schema": {
                                    "$ref": "#/components/schemas/49222af8b9e622717eb427d8633237e6"
                                }
                            }
                        }
                    },
                    "404": {
                        "description": "Not Found",
                        "content": {
                            "*/*": {
                                "schema": {
                                    "$ref": "#/components/schemas/207b98600ff36022b288945721524c2c"
                                }
                            }
                        }
                    }
                }
            }
        },
        "/api/articles/{slug}/favorite": {
            "post": {
                "operationId": "apiArticlesSlugFavoritePost",
                "parameters": [
                    {
                        "required": true,
                        "style": "simple",
                        "explode": false,
                        "schema": {
                            "$ref": "#/components/schemas/801051deb0ab9f05cdcc2330d9ff7c98"
                        },
                        "name": "slug",
                        "in": "path"
                    }
                ],
                "responses": {
                    "200": {
                        "description": "OK",
                        "content": {
                            "*/*": {
                                "schema": {
                                    "$ref": "#/components/schemas/7f9b8224fd6ec8df4b53c0c578a3ed1f"
                                }
                            }
                        }
                    },
                    "404": {
                        "description": "Invalid slug",
                        "content": {
                            "*/*": {
                                "schema": {
                                    "$ref": "#/components/schemas/e809c57ff10fd9bc78c38549267ebc03"
                                }
                            }
                        }
                    }
                }
            },
            "delete": {
                "operationId": "apiArticlesSlugFavoriteDelete",
                "parameters": [
                    {
                        "description": "Slug of the article",
                        "required": true,
                        "style": "simple",
                        "explode": false,
                        "schema": {
                            "$ref": "#/components/schemas/801051deb0ab9f05cdcc2330d9ff7c98"
                        },
                        "name": "slug",
                        "in": "path"
                    }
                ],
                "responses": {
                    "200": {
                        "description": "OK",
                        "content": {
                            "*/*": {
                                "schema": {
                                    "$ref": "#/components/schemas/f955e0ba6020ba68198df9cdf09aecac"
                                }
                            }
                        }
                    },
                    "404": {
                        "description": "Not Found",
                        "content": {
                            "*/*": {
                                "schema": {
                                    "$ref": "#/components/schemas/207b98600ff36022b288945721524c2c"
                                }
                            }
                        }
                    }
                }
            }
        },
        "/api/articles/{slug}/comments": {
            "get": {
                "operationId": "apiArticlesSlugCommentsGet",
                "parameters": [
                    {
                        "required": true,
                        "style": "simple",
                        "explode": false,
                        "schema": {
                            "$ref": "#/components/schemas/801051deb0ab9f05cdcc2330d9ff7c98"
                        },
                        "name": "slug",
                        "in": "path"
                    }
                ],
                "responses": {
                    "200": {
                        "description": "OK",
                        "content": {
                            "*/*": {
                                "schema": {
                                    "$ref": "#/components/schemas/af265cf074452b9b6a14064aaf70cfdf"
                                }
                            }
                        }
                    },
                    "404": {
                        "description": "Not Found",
                        "content": {
                            "*/*": {
                                "schema": {
                                    "$ref": "#/components/schemas/4923b9f03cb8ddda75dc1fd4925cbfe5"
                                }
                            }
                        }
                    }
                }
            },
            "post": {
                "operationId": "apiArticlesSlugCommentsPost",
                "parameters": [
                    {
                        "required": true,
                        "style": "simple",
                        "explode": false,
                        "schema": {
                            "$ref": "#/components/schemas/801051deb0ab9f05cdcc2330d9ff7c98"
                        },
                        "name": "slug",
                        "in": "path"
                    }
                ],
                "requestBody": {
                    "content": {
                        "*/*": {
                            "schema": {
                                "$ref": "#/components/schemas/c90180de6b6dbe04d0dda8a0772f1cf4"
                            }
                        }
                    },
                    "required": true
                },
                "responses": {
                    "201": {
                        "description": "Comment created",
                        "content": {
                            "*/*": {
                                "schema": {
                                    "$ref": "#/components/schemas/c45a397e7793bbe728eb1e3c043afdc2"
                                }
                            }
                        }
                    },
                    "404": {
                        "description": "Not Found",
                        "content": {
                            "*/*": {
                                "schema": {
                                    "$ref": "#/components/schemas/207b98600ff36022b288945721524c2c"
                                }
                            }
                        }
                    },
                    "422": {
                        "description": "Unprocessable Entity",
                        "content": {
                            "*/*": {
                                "schema": {
                                    "$ref": "#/components/schemas/207b98600ff36022b288945721524c2c"
                                }
                            }
                        }
                    }
                },
                "x-codegen-request-body-name": "body"
            }
        },
        "/api/articles/{slug}/comments/{id}": {
            "delete": {
                "operationId": "apiArticlesSlugCommentsIdDelete",
                "parameters": [
                    {
                        "required": true,
                        "style": "simple",
                        "explode": false,
                        "schema": {
                            "$ref": "#/components/schemas/801051deb0ab9f05cdcc2330d9ff7c98"
                        },
                        "name": "slug",
                        "in": "path"
                    },
                    {
                        "required": true,
                        "style": "simple",
                        "explode": false,
                        "schema": {
                            "$ref": "#/components/schemas/14d18c93b1e1920ef7540475867aa62c"
                        },
                        "name": "id",
                        "in": "path"
                    }
                ],
                "responses": {
                    "200": {
                        "description": "OK",
                        "content": {
                            "*/*": {
                                "schema": {
                                    "$ref": "#/components/schemas/703b03cc723e69768b1dce350b4ea0df"
                                }
                            }
                        }
                    },
                    "404": {
                        "description": "Not Found",
                        "content": {
                            "*/*": {
                                "schema": {
                                    "$ref": "#/components/schemas/4923b9f03cb8ddda75dc1fd4925cbfe5"
                                }
                            }
                        }
                    }
                }
            }
        },
        "/api/articles/{slug}": {
            "get": {
                "operationId": "apiArticlesSlugGet",
                "parameters": [
                    {
                        "description": "Slug of the article to retrieve",
                        "required": true,
                        "style": "simple",
                        "explode": false,
                        "schema": {
                            "$ref": "#/components/schemas/801051deb0ab9f05cdcc2330d9ff7c98"
                        },
                        "name": "slug",
                        "in": "path"
                    }
                ],
                "responses": {
                    "200": {
                        "description": "OK",
                        "content": {
                            "*/*": {
                                "schema": {
                                    "$ref": "#/components/schemas/0874daaa0e83e865e86c8554fb1dcaef"
                                }
                            }
                        }
                    },
                    "404": {
                        "description": "Invalid slug",
                        "content": {
                            "*/*": {
                                "schema": {
                                    "$ref": "#/components/schemas/207b98600ff36022b288945721524c2c"
                                }
                            }
                        }
                    }
                }
            }
        },
        "/api/tags": {
            "get": {
                "operationId": "apiTagsGet",
                "responses": {
                    "200": {
                        "description": "successful operation",
                        "content": {
                            "*/*": {
                                "schema": {
                                    "$ref": "#/components/schemas/99292ac0c43d81ae0c3aecd5ff4d3bdf"
                                }
                            }
                        }
                    },
                    "404": {
                        "description": "not found",
                        "content": {
                            "*/*": {
                                "schema": {
                                    "$ref": "#/components/schemas/207b98600ff36022b288945721524c2c"
                                }
                            }
                        }
                    }
                }
            }
        },
        "/api/profiles/{username}": {
            "get": {
                "operationId": "apiProfilesUsernameGet",
                "parameters": [
                    {
                        "required": true,
                        "style": "simple",
                        "explode": false,
                        "schema": {
                            "$ref": "#/components/schemas/801051deb0ab9f05cdcc2330d9ff7c98"
                        },
                        "name": "username",
                        "in": "path"
                    }
                ],
                "responses": {
                    "200": {
                        "description": "OK",
                        "content": {
                            "*/*": {
                                "schema": {
                                    "$ref": "#/components/schemas/8a99bc297537e5f82e499485b031e243"
                                }
                            }
                        }
                    },
                    "404": {
                        "description": "Not Found",
                        "content": {
                            "*/*": {
                                "schema": {
                                    "$ref": "#/components/schemas/b03243e043feaf883cba15a9d4b6d0ba"
                                }
                            }
                        }
                    }
                }
            }
        },
        "/api/profiles/{username}/follow": {
            "post": {
                "operationId": "apiProfilesUsernameFollowPost",
                "parameters": [
                    {
                        "description": "Username of the profile to follow",
                        "required": true,
                        "style": "simple",
                        "explode": false,
                        "schema": {
                            "$ref": "#/components/schemas/801051deb0ab9f05cdcc2330d9ff7c98"
                        },
                        "name": "username",
                        "in": "path"
                    }
                ],
                "responses": {
                    "200": {
                        "description": "OK",
                        "content": {
                            "*/*": {
                                "schema": {
                                    "$ref": "#/components/schemas/027173b66dfdc43b577bce236ac718ce"
                                }
                            }
                        }
                    },
                    "404": {
                        "description": "Invalid username",
                        "content": {
                            "*/*": {
                                "schema": {
                                    "$ref": "#/components/schemas/fd5f97374c48bb8dbaa27ad83f642a32"
                                }
                            }
                        }
                    },
                    "422": {
                        "description": "Unprocessable Entity",
                        "content": {
                            "*/*": {
                                "schema": {
                                    "$ref": "#/components/schemas/e71ae9274f9b835d9212dce5be867ff3"
                                }
                            }
                        }
                    }
                }
            }
        },
        "/profiles/{username}/follow": {
            "post": {
                "operationId": "profilesUsernameFollowPost",
                "parameters": [
                    {
                        "required": true,
                        "style": "simple",
                        "explode": false,
                        "schema": {
                            "$ref": "#/components/schemas/801051deb0ab9f05cdcc2330d9ff7c98"
                        },
                        "name": "username",
                        "in": "path"
                    }
                ],
                "responses": {
                    "200": {
                        "description": "OK",
                        "content": {
                            "*/*": {
                                "schema": {
                                    "$ref": "#/components/schemas/a15bf02cda67e4412d0e183de48bbab2"
                                }
                            }
                        }
                    },
                    "404": {
                        "description": "Not Found",
                        "content": {
                            "*/*": {
                                "schema": {
                                    "$ref": "#/components/schemas/976f0f414a53f86442be2a095e2f73bf"
                                }
                            }
                        }
                    },
                    "422": {
                        "description": "Unprocessable Entity",
                        "content": {
                            "*/*": {
                                "schema": {
                                    "$ref": "#/components/schemas/35474ed318e28de5edc3c68fc4a85c6f"
                                }
                            }
                        }
                    }
                }
            },
            "delete": {
                "operationId": "profilesUsernameFollowDelete",
                "parameters": [
                    {
                        "required": true,
                        "style": "simple",
                        "explode": false,
                        "schema": {
                            "$ref": "#/components/schemas/801051deb0ab9f05cdcc2330d9ff7c98"
                        },
                        "name": "username",
                        "in": "path"
                    }
                ],
                "responses": {
                    "200": {
                        "description": "Profile unfollowed",
                        "content": {
                            "*/*": {
                                "schema": {
                                    "$ref": "#/components/schemas/027173b66dfdc43b577bce236ac718ce"
                                }
                            }
                        }
                    },
                    "404": {
                        "description": "Profile not found",
                        "content": {
                            "*/*": {
                                "schema": {
                                    "$ref": "#/components/schemas/207b98600ff36022b288945721524c2c"
                                }
                            }
                        }
                    },
                    "422": {
                        "description": "Unprocessable Entity",
                        "content": {
                            "*/*": {
                                "schema": {
                                    "$ref": "#/components/schemas/207b98600ff36022b288945721524c2c"
                                }
                            }
                        }
                    }
                }
            }
        },
        "/api/users": {
            "post": {
                "operationId": "apiUsersPost",
                "requestBody": {
                    "content": {
                        "*/*": {
                            "schema": {
                                "$ref": "#/components/schemas/9db0cb959470a89ac60dead7238659b8"
                            }
                        }
                    },
                    "required": true
                },
                "responses": {
                    "201": {
                        "description": "User created",
                        "content": {
                            "*/*": {
                                "schema": {
                                    "$ref": "#/components/schemas/c66e2e52908b8745fcd5e24c1212f419"
                                }
                            }
                        }
                    },
                    "422": {
                        "description": "Validation or database error",
                        "content": {
                            "*/*": {
                                "schema": {
                                    "$ref": "#/components/schemas/207b98600ff36022b288945721524c2c"
                                }
                            }
                        }
                    }
                },
                "x-codegen-request-body-name": "body"
            }
        },
        "/api/users/login": {
            "post": {
                "operationId": "apiUsersLoginPost",
                "requestBody": {
                    "content": {
                        "*/*": {
                            "schema": {
                                "$ref": "#/components/schemas/709795c415f9b2dd5734ade2edeb50db"
                            }
                        }
                    },
                    "required": true
                },
                "responses": {
                    "200": {
                        "description": "OK",
                        "content": {
                            "*/*": {
                                "schema": {
                                    "$ref": "#/components/schemas/7ba2f0c06ee27d69dc1db8764ed8021b"
                                }
                            }
                        }
                    },
                    "403": {
                        "description": "Forbidden",
                        "content": {
                            "*/*": {
                                "schema": {
                                    "$ref": "#/components/schemas/207b98600ff36022b288945721524c2c"
                                }
                            }
                        }
                    },
                    "422": {
                        "description": "Unprocessable Entity",
                        "content": {
                            "*/*": {
                                "schema": {
                                    "$ref": "#/components/schemas/207b98600ff36022b288945721524c2c"
                                }
                            }
                        }
                    }
                },
                "x-codegen-request-body-name": "body"
            }
        },
        "/user": {
            "get": {
                "operationId": "userGet",
                "parameters": [
                    {
                        "description": "Authentication token in the format 'Token <token>'",
                        "required": true,
                        "style": "simple",
                        "explode": false,
                        "schema": {
                            "$ref": "#/components/schemas/801051deb0ab9f05cdcc2330d9ff7c98"
                        },
                        "name": "Authorization",
                        "in": "header"
                    }
                ],
                "responses": {
                    "200": {
                        "description": "OK",
                        "content": {
                            "*/*": {
                                "schema": {
                                    "$ref": "#/components/schemas/59cb184e42849366e2e65573cbedf240"
                                }
                            }
                        }
                    }
                }
            },
            "put": {
                "operationId": "userPut",
                "requestBody": {
                    "content": {
                        "*/*": {
                            "schema": {
                                "$ref": "#/components/schemas/703431ab26f3fbb46af82270f561dc0c"
                            }
                        }
                    },
                    "required": true
                },
                "responses": {
                    "200": {
                        "description": "OK",
                        "content": {
                            "*/*": {
                                "schema": {
                                    "$ref": "#/components/schemas/c66e2e52908b8745fcd5e24c1212f419"
                                }
                            }
                        }
                    },
                    "422": {
                        "description": "Unprocessable Entity",
                        "content": {
                            "*/*": {
                                "schema": {
                                    "$ref": "#/components/schemas/77e51be78297f19c205dd38ca21d11bb"
                                }
                            }
                        }
                    }
                },
                "x-codegen-request-body-name": "body"
            }
        },
        "/api/user": {
            "get": {
                "operationId": "apiUserGet",
                "responses": {
                    "200": {
                        "description": "OK",
                        "content": {
                            "*/*": {
                                "schema": {
                                    "$ref": "#/components/schemas/c66e2e52908b8745fcd5e24c1212f419"
                                }
                            }
                        }
                    }
                }
            },
            "put": {
                "operationId": "apiUserPut",
                "requestBody": {
                    "content": {
                        "*/*": {
                            "schema": {
                                "$ref": "#/components/schemas/9340e0e0d50ffa3369f38f65f033afe5"
                            }
                        }
                    },
                    "required": true
                },
                "responses": {
                    "200": {
                        "description": "OK",
                        "content": {
                            "*/*": {
                                "schema": {
                                    "$ref": "#/components/schemas/33dabb7ddb2a23324e1159d3226c5204"
                                }
                            }
                        }
                    },
                    "422": {
                        "description": "Unprocessable Entity",
                        "content": {
                            "*/*": {
                                "schema": {
                                    "$ref": "#/components/schemas/94217b95135a4f56e61d8e626a57527c"
                                }
                            }
                        }
                    }
                },
                "x-codegen-request-body-name": "body"
            }
        }
    },
    "components": {
        "schemas": {
            "801051deb0ab9f05cdcc2330d9ff7c98": {
                "type": "string"
            },
            "14d18c93b1e1920ef7540475867aa62c": {
                "type": "integer",
                "format": "int64"
            },
            "332e82c6bdd5ac3bf5ea0510ba61025f": {
                "properties": {
                    "articles": {
                        "items": {
                            "properties": {},
                            "type": "object"
                        },
                        "type": "array"
                    },
                    "articlesCount": {
                        "type": "integer",
                        "format": "int32"
                    }
                },
                "type": "object"
            },
            "4d3603a0b1508e557c000c21e6de2ad5": {
                "properties": {
                    "article": {
                        "properties": {
                            "title": {
                                "type": "string"
                            },
                            "description": {
                                "type": "string"
                            },
                            "body": {
                                "type": "string"
                            },
                            "tagList": {
                                "items": {
                                    "type": "string"
                                },
                                "type": "array"
                            }
                        },
                        "type": "object"
                    }
                },
                "type": "object"
            },
            "06865e445c5dc508f4e842f390217f80": {
                "properties": {
                    "article": {
                        "properties": {
                            "title": {
                                "type": "string"
                            },
                            "slug": {
                                "type": "string"
                            },
                            "description": {
                                "type": "string"
                            },
                            "body": {
                                "type": "string"
                            },
                            "createdAt": {
                                "type": "string"
                            },
                            "updatedAt": {
                                "type": "string"
                            },
                            "author": {
                                "properties": {
                                    "username": {
                                        "type": "string"
                                    },
                                    "bio": {
                                        "type": "string"
                                    },
                                    "image": {
                                        "type": "string"
                                    },
                                    "following": {
                                        "type": "boolean"
                                    }
                                },
                                "type": "object"
                            },
                            "tagList": {
                                "items": {
                                    "type": "string"
                                },
                                "type": "array"
                            },
                            "favorited": {
                                "type": "boolean"
                            },
                            "favoritesCount": {
                                "type": "integer",
                                "format": "int64"
                            }
                        },
                        "type": "object"
                    }
                },
                "type": "object"
            },
            "207b98600ff36022b288945721524c2c": {
                "properties": {
                    "errors": {
                        "additionalProperties": {
                            "type": "string"
                        },
                        "type": "object"
                    }
                },
                "type": "object"
            },
            "f3dbb1c7998397f9739dd8ca035645bc": {
                "properties": {
                    "article": {
                        "properties": {
                            "title": {
                                "type": "string"
                            },
                            "description": {
                                "type": "string"
                            },
                            "body": {
                                "type": "string"
                            },
                            "tagList": {
                                "items": {
                                    "type": "string"
                                },
                                "type": "array"
                            }
                        },
                        "type": "object",
                        "required": [
                            "title"
                        ]
                    }
                },
                "type": "object"
            },
            "b86f86ff4e88d014b319f07dcbcaa18a": {
                "properties": {
                    "article": {
                        "properties": {
                            "title": {
                                "type": "string"
                            },
                            "slug": {
                                "type": "string"
                            },
                            "description": {
                                "type": "string"
                            },
                            "body": {
                                "type": "string"
                            },
                            "createdAt": {
                                "type": "string"
                            },
                            "updatedAt": {
                                "type": "string"
                            },
                            "author": {
                                "properties": {
                                    "username": {
                                        "type": "string"
                                    },
                                    "bio": {
                                        "type": "string"
                                    },
                                    "image": {
                                        "type": "string",
                                        "nullable": true
                                    },
                                    "following": {
                                        "type": "boolean"
                                    }
                                },
                                "type": "object"
                            },
                            "tagList": {
                                "items": {
                                    "type": "string"
                                },
                                "type": "array"
                            },
                            "favorited": {
                                "type": "boolean"
                            },
                            "favoritesCount": {
                                "type": "integer",
                                "format": "int64"
                            }
                        },
                        "type": "object"
                    }
                },
                "type": "object"
            },
            "49222af8b9e622717eb427d8633237e6": {
                "properties": {
                    "article": {
                        "type": "string"
                    }
                },
                "type": "object"
            },
            "7f9b8224fd6ec8df4b53c0c578a3ed1f": {
                "properties": {
                    "article": {
                        "properties": {
                            "slug": {
                                "type": "string"
                            },
                            "title": {
                                "type": "string"
                            },
                            "description": {
                                "type": "string"
                            },
                            "body": {
                                "type": "string"
                            },
                            "tagList": {
                                "items": {
                                    "type": "string"
                                },
                                "type": "array"
                            },
                            "createdAt": {
                                "type": "string",
                                "format": "date-time"
                            },
                            "updatedAt": {
                                "type": "string",
                                "format": "date-time"
                            },
                            "favorited": {
                                "type": "boolean"
                            },
                            "favoritesCount": {
                                "type": "integer"
                            },
                            "author": {
                                "properties": {
                                    "username": {
                                        "type": "string"
                                    },
                                    "bio": {
                                        "type": "string"
                                    },
                                    "image": {
                                        "type": "string"
                                    },
                                    "following": {
                                        "type": "boolean"
                                    }
                                },
                                "type": "object"
                            }
                        },
                        "type": "object"
                    }
                },
                "type": "object"
            },
            "e809c57ff10fd9bc78c38549267ebc03": {
                "properties": {
                    "errors": {
                        "properties": {
                            "articles": {
                                "items": {
                                    "type": "string"
                                },
                                "type": "array"
                            }
                        },
                        "type": "object"
                    }
                },
                "type": "object"
            },
            "f955e0ba6020ba68198df9cdf09aecac": {
                "properties": {
                    "article": {
                        "properties": {
                            "title": {
                                "type": "string"
                            },
                            "slug": {
                                "type": "string"
                            },
                            "description": {
                                "type": "string"
                            },
                            "body": {
                                "type": "string"
                            },
                            "createdAt": {
                                "type": "string",
                                "format": "date-time"
                            },
                            "updatedAt": {
                                "type": "string",
                                "format": "date-time"
                            },
                            "author": {
                                "properties": {
                                    "username": {
                                        "type": "string"
                                    },
                                    "bio": {
                                        "type": "string"
                                    },
                                    "following": {
                                        "type": "boolean"
                                    }
                                },
                                "type": "object"
                            },
                            "tagList": {
                                "items": {
                                    "type": "string"
                                },
                                "type": "array"
                            },
                            "favorited": {
                                "type": "boolean"
                            },
                            "favoritesCount": {
                                "type": "integer"
                            }
                        },
                        "type": "object"
                    }
                },
                "type": "object"
            },
            "af265cf074452b9b6a14064aaf70cfdf": {
                "properties": {
                    "comments": {
                        "items": {
                            "properties": {
                                "id": {
                                    "type": "integer",
                                    "format": "int64"
                                },
                                "body": {
                                    "type": "string"
                                },
                                "createdAt": {
                                    "type": "string",
                                    "format": "date-time"
                                },
                                "updatedAt": {
                                    "type": "string",
                                    "format": "date-time"
                                },
                                "author": {
                                    "properties": {
                                        "username": {
                                            "type": "string"
                                        },
                                        "bio": {
                                            "type": "string"
                                        },
                                        "image": {
                                            "type": "string"
                                        },
                                        "following": {
                                            "type": "boolean"
                                        }
                                    },
                                    "type": "object"
                                }
                            },
                            "type": "object"
                        },
                        "type": "array"
                    }
                },
                "type": "object"
            },
            "4923b9f03cb8ddda75dc1fd4925cbfe5": {
                "properties": {
                    "errors": {
                        "additionalProperties": {
                            "items": {
                                "type": "string"
                            },
                            "type": "array"
                        },
                        "type": "object"
                    }
                },
                "type": "object"
            },
            "c90180de6b6dbe04d0dda8a0772f1cf4": {
                "properties": {
                    "comment": {
                        "properties": {
                            "body": {
                                "type": "string"
                            }
                        },
                        "type": "object",
                        "required": [
                            "body"
                        ]
                    }
                },
                "type": "object",
                "required": [
                    "comment"
                ]
            },
            "c45a397e7793bbe728eb1e3c043afdc2": {
                "properties": {
                    "comment": {
                        "properties": {
                            "id": {
                                "type": "integer",
                                "format": "int64"
                            },
                            "body": {
                                "type": "string"
                            },
                            "createdAt": {
                                "type": "string"
                            },
                            "updatedAt": {
                                "type": "string"
                            },
                            "author": {
                                "properties": {
                                    "username": {
                                        "type": "string"
                                    },
                                    "bio": {
                                        "type": "string"
                                    },
                                    "image": {
                                        "type": "string"
                                    },
                                    "following": {
                                        "type": "boolean"
                                    }
                                },
                                "type": "object"
                            }
                        },
                        "type": "object"
                    }
                },
                "type": "object"
            },
            "703b03cc723e69768b1dce350b4ea0df": {
                "properties": {
                    "comment": {
                        "type": "string"
                    }
                },
                "type": "object"
            },
            "0874daaa0e83e865e86c8554fb1dcaef": {
                "properties": {
                    "article": {
                        "properties": {
                            "slug": {
                                "type": "string"
                            },
                            "title": {
                                "type": "string"
                            },
                            "description": {
                                "type": "string"
                            },
                            "body": {
                                "type": "string"
                            },
                            "createdAt": {
                                "type": "string",
                                "format": "date-time"
                            },
                            "updatedAt": {
                                "type": "string",
                                "format": "date-time"
                            },
                            "author": {
                                "properties": {
                                    "username": {
                                        "type": "string"
                                    },
                                    "bio": {
                                        "type": "string"
                                    },
                                    "image": {
                                        "type": "string"
                                    },
                                    "following": {
                                        "type": "boolean"
                                    }
                                },
                                "type": "object"
                            },
                            "tagList": {
                                "items": {
                                    "type": "string"
                                },
                                "type": "array"
                            },
                            "favorited": {
                                "type": "boolean"
                            },
                            "favoritesCount": {
                                "type": "integer",
                                "format": "int32"
                            }
                        },
                        "type": "object"
                    }
                },
                "type": "object"
            },
            "99292ac0c43d81ae0c3aecd5ff4d3bdf": {
                "properties": {
                    "tags": {
                        "items": {
                            "type": "string"
                        },
                        "type": "array"
                    }
                },
                "type": "object"
            },
            "8a99bc297537e5f82e499485b031e243": {
                "properties": {
                    "profile": {
                        "properties": {
                            "username": {
                                "type": "string"
                            },
                            "bio": {
                                "type": "string"
                            },
                            "image": {
                                "type": "string"
                            },
                            "following": {
                                "type": "boolean"
                            }
                        },
                        "type": "object",
                        "required": [
                            "bio",
                            "following",
                            "image",
                            "username"
                        ]
                    }
                },
                "type": "object",
                "required": [
                    "profile"
                ]
            },
            "b03243e043feaf883cba15a9d4b6d0ba": {
                "properties": {
                    "errors": {
                        "additionalProperties": {
                            "items": {
                                "type": "string"
                            },
                            "type": "array"
                        },
                        "type": "object"
                    }
                },
                "type": "object",
                "required": [
                    "errors"
                ]
            },
            "027173b66dfdc43b577bce236ac718ce": {
                "properties": {
                    "profile": {
                        "properties": {
                            "username": {
                                "type": "string"
                            },
                            "bio": {
                                "type": "string"
                            },
                            "image": {
                                "type": "string"
                            },
                            "following": {
                                "type": "boolean"
                            }
                        },
                        "type": "object"
                    }
                },
                "type": "object"
            },
            "fd5f97374c48bb8dbaa27ad83f642a32": {
                "properties": {
                    "errors": {
                        "properties": {
                            "profile": {
                                "items": {
                                    "type": "string"
                                },
                                "type": "array"
                            }
                        },
                        "type": "object"
                    }
                },
                "type": "object"
            },
            "e71ae9274f9b835d9212dce5be867ff3": {
                "properties": {
                    "errors": {
                        "properties": {
                            "database": {
                                "items": {
                                    "type": "string"
                                },
                                "type": "array"
                            }
                        },
                        "type": "object"
                    }
                },
                "type": "object"
            },
            "a15bf02cda67e4412d0e183de48bbab2": {
                "properties": {
                    "profile": {
                        "properties": {
                            "username": {
                                "type": "string"
                            },
                            "bio": {
                                "type": "string"
                            },
                            "image": {
                                "type": "string",
                                "nullable": true
                            },
                            "following": {
                                "type": "boolean"
                            }
                        },
                        "type": "object"
                    }
                },
                "type": "object"
            },
            "976f0f414a53f86442be2a095e2f73bf": {
                "properties": {
                    "errors": {
                        "properties": {
                            "profile": {
                                "type": "string"
                            }
                        },
                        "type": "object"
                    }
                },
                "type": "object"
            },
            "35474ed318e28de5edc3c68fc4a85c6f": {
                "properties": {
                    "errors": {
                        "properties": {
                            "database": {
                                "type": "string"
                            }
                        },
                        "type": "object"
                    }
                },
                "type": "object"
            },
            "9db0cb959470a89ac60dead7238659b8": {
                "properties": {
                    "username": {
                        "type": "string",
                        "maxLength": 255,
                        "minLength": 4,
                        "pattern": "^[A-Za-z0-9]+$"
                    },
                    "email": {
                        "type": "string",
                        "format": "email"
                    },
                    "password": {
                        "type": "string",
                        "maxLength": 255,
                        "minLength": 8
                    },
                    "bio": {
                        "type": "string",
                        "maxLength": 1024
                    },
                    "image": {
                        "type": "string",
                        "format": "url"
                    }
                },
                "type": "object",
                "required": [
                    "email",
                    "password",
                    "username"
                ]
            },
            "c66e2e52908b8745fcd5e24c1212f419": {
                "properties": {
                    "user": {
                        "properties": {
                            "username": {
                                "type": "string"
                            },
                            "email": {
                                "type": "string"
                            },
                            "bio": {
                                "type": "string"
                            },
                            "image": {
                                "type": "string"
                            },
                            "token": {
                                "type": "string"
                            }
                        },
                        "type": "object"
                    }
                },
                "type": "object"
            },
            "709795c415f9b2dd5734ade2edeb50db": {
                "properties": {
                    "user": {
                        "properties": {
                            "email": {
                                "type": "string",
                                "format": "email"
                            },
                            "password": {
                                "type": "string",
                                "format": "password"
                            }
                        },
                        "type": "object",
                        "required": [
                            "email",
                            "password"
                        ]
                    }
                },
                "type": "object",
                "required": [
                    "user"
                ]
            },
            "7ba2f0c06ee27d69dc1db8764ed8021b": {
                "properties": {
                    "user": {
                        "properties": {
                            "username": {
                                "type": "string"
                            },
                            "email": {
                                "type": "string",
                                "format": "email"
                            },
                            "bio": {
                                "type": "string"
                            },
                            "image": {
                                "type": "string"
                            },
                            "token": {
                                "type": "string"
                            }
                        },
                        "type": "object"
                    }
                },
                "type": "object"
            },
            "59cb184e42849366e2e65573cbedf240": {
                "properties": {
                    "user": {
                        "properties": {
                            "username": {
                                "type": "string"
                            },
                            "email": {
                                "type": "string",
                                "format": "email"
                            },
                            "bio": {
                                "type": "string"
                            },
                            "image": {
                                "type": "string",
                                "nullable": true
                            },
                            "token": {
                                "type": "string"
                            }
                        },
                        "type": "object",
                        "required": [
                            "bio",
                            "email",
                            "token",
                            "username"
                        ]
                    }
                },
                "type": "object"
            },
            "703431ab26f3fbb46af82270f561dc0c": {
                "properties": {
                    "user": {
                        "properties": {
                            "username": {
                                "type": "string"
                            },
                            "email": {
                                "type": "string"
                            },
                            "password": {
                                "type": "string"
                            },
                            "bio": {
                                "type": "string"
                            },
                            "image": {
                                "type": "string"
                            }
                        },
                        "type": "object",
                        "required": [
                            "email",
                            "password",
                            "username"
                        ]
                    }
                },
                "type": "object"
            },
            "77e51be78297f19c205dd38ca21d11bb": {
                "properties": {
                    "errors": {
                        "properties": {},
                        "type": "object"
                    }
                },
                "type": "object"
            },
            "9340e0e0d50ffa3369f38f65f033afe5": {
                "properties": {
                    "user": {
                        "properties": {
                            "username": {
                                "type": "string"
                            },
                            "email": {
                                "type": "string",
                                "format": "email"
                            },
                            "password": {
                                "type": "string"
                            },
                            "bio": {
                                "type": "string"
                            },
                            "image": {
                                "type": "string"
                            }
                        },
                        "type": "object",
                        "required": [
                            "email",
                            "password",
                            "username"
                        ]
                    }
                },
                "type": "object"
            },
            "33dabb7ddb2a23324e1159d3226c5204": {
                "properties": {
                    "user": {
                        "properties": {},
                        "type": "object"
                    }
                },
                "type": "object"
            },
            "94217b95135a4f56e61d8e626a57527c": {
                "type": "object"
            }
        }
    }
}